demopy/__init__.py
demopy/constants.py
demopy/tools.py
demopy/cli/__init__.py
demopy/cli/puml.py
demopy/puml/__init__.py
demopy/puml/erd.py
demopy/puml/mindmap.py
demopy/puml/simple.py
demopy/puml/synchro.py
demo_py-0.0.1a12.dist-info/LICENSE
demo_py-0.0.1a12.dist-info/METADATA
demo_py-0.0.1a12.dist-info/WHEEL
demo_py-0.0.1a12.dist-info/entry_points.txt
demo_py-0.0.1a12.dist-info/top_level.txt
demo_py-0.0.1a12.dist-info/RECORD
